aws_sts_tool/__init__.py
aws_sts_tool/_version.py
aws_sts_tool/cli.py
aws_sts_tool/helpers/__init__.py
aws_sts_tool/helpers/datetimeencoder.py
aws_sts_tool-1.0.3.dist-info/LICENSE
aws_sts_tool-1.0.3.dist-info/METADATA
aws_sts_tool-1.0.3.dist-info/WHEEL
aws_sts_tool-1.0.3.dist-info/entry_points.txt
aws_sts_tool-1.0.3.dist-info/top_level.txt
aws_sts_tool-1.0.3.dist-info/RECORD
