Metadata-Version: 2.1
Name: aws-sts-tool
Version: 1.0.3
Summary: A CLI tool to help assume AWS role via STS.
Home-page: https://github.com/farazmd/aws-sts-tool
Author: Mohammad Faraz
Author-email: farazm708@gmail.com
License: UNKNOWN
Platform: UNKNOWN
Classifier: Programming Language :: Python :: 3
Classifier: License :: OSI Approved :: MIT License
Classifier: Operating System :: OS Independent
Requires-Python: >=3.7
License-File: LICENSE
Requires-Dist: botocore (==1.21.40)
Requires-Dist: boto3 (==1.18.40)
